wordsapy/__init__.py
wordsapy/dict_obj.py
wordsapy/dictionary.py
wordsapy/exceptions.py
wordsapy/wordsapy.py
wordsapy-1.1.1.dist-info/LICENSE
wordsapy-1.1.1.dist-info/METADATA
wordsapy-1.1.1.dist-info/WHEEL
wordsapy-1.1.1.dist-info/top_level.txt
wordsapy-1.1.1.dist-info/RECORD
