Metadata-Version: 2.1
Name: wordsapy
Version: 1.1.1
Summary: Wordsapy is a python integration for the WordsAPI, that allows developers to retrieve information about English words like a dictionary.
Home-page: https://github.com/backrndsource/wordsapy
Author: Sergio Contreras Agustí (backrndsource)
Author-email: backrndsource@gmail.com
License: UNKNOWN
Keywords: words,dictionarywordsapi,api,wrapper,interface,client,database
Platform: UNKNOWN
Classifier: Development Status :: 5 - Production/Stable
Classifier: Intended Audience :: Developers
Classifier: Topic :: Software Development :: Libraries
Classifier: Programming Language :: Python
Classifier: Programming Language :: Python :: 3
Classifier: Programming Language :: Python :: 3.5
Classifier: Programming Language :: Python :: 3.6
Classifier: Programming Language :: Python :: 3.7
Classifier: Programming Language :: Python :: 3.8
Classifier: Programming Language :: Python :: 3.9
Classifier: License :: OSI Approved :: MIT License
Classifier: Operating System :: OS Independent
Requires-Python: >=3.5
Requires-Dist: requests
